jupyter_ui_poll/__init__.py
jupyter_ui_poll/_async_thread.py
jupyter_ui_poll/_poll.py
jupyter_ui_poll/_version.py
jupyter_ui_poll-1.0.0.dist-info/LICENSE
jupyter_ui_poll-1.0.0.dist-info/METADATA
jupyter_ui_poll-1.0.0.dist-info/WHEEL
jupyter_ui_poll-1.0.0.dist-info/top_level.txt
jupyter_ui_poll-1.0.0.dist-info/zip-safe
jupyter_ui_poll-1.0.0.dist-info/RECORD
