Metadata-Version: 2.1
Name: jupyter-ui-poll
Version: 1.0.0
Summary: Block jupyter cell execution while interacting with widgets
Home-page: https://github.com/kirill888/jupyter-ui-poll
Author: Kirill Kouzoubov
Author-email: kirill888@gmail.com
License: MIT License
Project-URL: Documentation, https://jupyter-ui-poll.readthedocs.io/en/latest/
Project-URL: Bug Reporting, https://github.com/kirill888/jupyter-ui-poll/issues
Keywords: jupyter,ipywidgets
Platform: any
Classifier: Framework :: Jupyter
Classifier: Intended Audience :: Developers
Classifier: Development Status :: 5 - Production/Stable
Classifier: Operating System :: OS Independent
Classifier: License :: OSI Approved :: MIT License
Classifier: Programming Language :: Python :: 3.8
Classifier: Programming Language :: Python :: 3.9
Classifier: Programming Language :: Python :: 3.10
Classifier: Programming Language :: Python :: 3.11
Classifier: Programming Language :: Python :: 3.12
Requires-Python: >=3.8
Provides-Extra: dev
Provides-Extra: docs
